databricksPackageVTX/__init__.py
databricksPackageVTX/module1.py
databricksPackageVTX/module2.py
databricksPackageVTX-0.11.dist-info/METADATA
databricksPackageVTX-0.11.dist-info/WHEEL
databricksPackageVTX-0.11.dist-info/top_level.txt
databricksPackageVTX-0.11.dist-info/RECORD
